epson_printer/__init__.py
epson_printer/epsonprinter.py
epson_printer/testpage.py
epson_printer/utils.py
epson_printer/test/__init__.py
epson_printer/test/printable_image.py
python_epson_printer-1.12.0.dist-info/LICENSE
python_epson_printer-1.12.0.dist-info/METADATA
python_epson_printer-1.12.0.dist-info/WHEEL
python_epson_printer-1.12.0.dist-info/top_level.txt
python_epson_printer-1.12.0.dist-info/RECORD
