Metadata-Version: 2.1
Name: python-epson-printer
Version: 1.12.0
Summary: A library to control Epson thermal printers based on ESC/POS language
Home-page: https://github.com/benoitguigal/python-epson-printer/
Author: Benoit Guigal
Author-email: benoit.guigal@gmail.com
License: MIT
Keywords: epson printer escpos
Platform: UNKNOWN
Classifier: Development Status :: 4 - Beta
Classifier: Intended Audience :: Developers
Classifier: Topic :: Software Development :: Build Tools
Classifier: License :: OSI Approved :: MIT License
Classifier: Programming Language :: Python :: 2
Classifier: Programming Language :: Python :: 2.6
Classifier: Programming Language :: Python :: 2.7
Requires-Dist: pyusb (>=1.0.0)
